Metadata-Version: 1.1
Name: GROUPmath
Version: 0.2
Summary: A data structure called group
Home-page: https://github.com/SadafShafi/GROUP
Author: Sadaf Shafi
Author-email: daee.sadaf2011@gmail.com
License: MIT
Download-URL: https://github.com/SadafShafi/GROUP.git
Platform: UNKNOWN
